.bzrignore
.gitignore
.travis.yml
CHANGES.rst
CONTRIBUTORS.txt
COPYRIGHT.txt
LICENSE.txt
MANIFEST.in
README.rst
TODO.txt
setup.cfg
setup.py
tox.ini
docs/Makefile
docs/api.rst
docs/changes.rst
docs/conf.py
docs/index.rst
docs/narr.rst
docs/.static/logo_hi.gif
docs/.static/repoze.css
repoze/__init__.py
repoze.folder.egg-info/PKG-INFO
repoze.folder.egg-info/SOURCES.txt
repoze.folder.egg-info/dependency_links.txt
repoze.folder.egg-info/entry_points.txt
repoze.folder.egg-info/namespace_packages.txt
repoze.folder.egg-info/not-zip-safe
repoze.folder.egg-info/requires.txt
repoze.folder.egg-info/top_level.txt
repoze/folder/__init__.py
repoze/folder/_compat.py
repoze/folder/events.py
repoze/folder/interfaces.py
repoze/folder/tests.py